README.md
setup.py
openlobby/__init__.py
openlobby/schema.py
openlobby/settings.py
openlobby/urls.py
openlobby/wsgi.py
openlobby.egg-info/PKG-INFO
openlobby.egg-info/SOURCES.txt
openlobby.egg-info/dependency_links.txt
openlobby.egg-info/top_level.txt
openlobby/core/__init__.py
openlobby/core/admin.py
openlobby/core/apps.py
openlobby/core/auth.py
openlobby/core/documents.py
openlobby/core/middleware.py
openlobby/core/models.py
openlobby/core/openid.py
openlobby/core/search.py
openlobby/core/views.py
openlobby/core/api/__init__.py
openlobby/core/api/mutations.py
openlobby/core/api/paginator.py
openlobby/core/api/sanitizers.py
openlobby/core/api/schema.py
openlobby/core/api/types.py
openlobby/core/api/utils.py
openlobby/core/migrations/0001_initial.py
openlobby/core/migrations/0002_auto_20180116_2349.py
openlobby/core/migrations/0003_auto_20180117_0030.py
openlobby/core/migrations/0004_user_is_author.py
openlobby/core/migrations/0005_auto_20180208_1210.py
openlobby/core/migrations/0006_auto_20180208_1544.py
openlobby/core/migrations/0007_auto_20180209_1809.py
openlobby/core/migrations/0008_loginattempt_openid_uid.py
openlobby/core/migrations/0009_auto_20180217_1850.py
openlobby/core/migrations/0010_user_has_colliding_name.py
openlobby/core/migrations/0011_report_is_draft.py
openlobby/core/migrations/__init__.py
tests/mutations/__init__.py
tests/mutations/test_create_report.py
tests/mutations/test_login.py
tests/mutations/test_login_by_shortcut.py
tests/mutations/test_update_report.py
tests/mutations/snapshots/__init__.py
tests/mutations/snapshots/snap_test_create_report.py
tests/mutations/snapshots/snap_test_login.py
tests/mutations/snapshots/snap_test_login_by_shortcut.py
tests/mutations/snapshots/snap_test_update_report.py
tests/schema/__init__.py
tests/schema/test_authors.py
tests/schema/test_login_shortcuts.py
tests/schema/test_node.py
tests/schema/test_report_drafts.py
tests/schema/test_search_reports.py
tests/schema/test_viewer.py
tests/schema/snapshots/__init__.py
tests/schema/snapshots/snap_test_authors.py
tests/schema/snapshots/snap_test_login_shortcuts.py
