Metadata-Version: 1.1
Name: openlobby
Version: 0.1.0
Summary: Open Lobby Server
Home-page: https://github.com/openlobby/openlobby-server
Author: Jan Bednarik
Author-email: jan.bednarik@gmail.com
License: MIT
Platform: UNKNOWN
Classifier: Development Status :: 4 - Beta
Classifier: License :: OSI Approved :: MIT License
Classifier: Programming Language :: Python :: 3
Classifier: Programming Language :: Python :: 3.3
Classifier: Programming Language :: Python :: 3.4
Classifier: Programming Language :: Python :: 3.5
